duo_ai/__init__.py
duo_ai/algorithms/__init__.py
duo_ai/algorithms/always.py
duo_ai/algorithms/logit.py
duo_ai/algorithms/ppo.py
duo_ai/algorithms/pyod.py
duo_ai/algorithms/random.py
duo_ai/core/__init__.py
duo_ai/core/algorithm.py
duo_ai/core/config.py
duo_ai/core/environment.py
duo_ai/core/evaluator.py
duo_ai/core/policy.py
duo_ai/environments/__init__.py
duo_ai/models/__init__.py
duo_ai/models/impala.py
duo_ai/models/ppo.py
duo_ai/policies/__init__.py
duo_ai/policies/always.py
duo_ai/policies/logit.py
duo_ai/policies/ppo.py
duo_ai/policies/pyod.py
duo_ai/policies/random.py
duo_ai/utils/__init__.py
duo_ai/utils/evaluation.py
duo_ai/utils/global_variables.py
duo_ai/utils/logging.py
duo_ai/utils/model.py
duo_ai/utils/wandb.py
duo_ai-1.0.1.dist-info/licenses/LICENSE
duo_ai-1.0.1.dist-info/METADATA
duo_ai-1.0.1.dist-info/WHEEL
duo_ai-1.0.1.dist-info/top_level.txt
duo_ai-1.0.1.dist-info/RECORD
