Metadata-Version: 2.4
Name: duo-ai
Version: 1.0.1
Summary: DuoAI: Two-System AI Agents
Requires-Python: >=3.8
License-File: LICENSE
Requires-Dist: omegaconf>=2.3.0
Requires-Dist: gym>=0.26.2
Requires-Dist: torch>=2.1.2
Requires-Dist: wandb>=0.19.11
Requires-Dist: scikit-learn
Requires-Dist: numba
Provides-Extra: docs
Requires-Dist: sphinx; extra == "docs"
Requires-Dist: sphinx-autoapi; extra == "docs"
Requires-Dist: sphinx_copybutton; extra == "docs"
Requires-Dist: furo; extra == "docs"
Dynamic: license-file
